.gitattributes
.gitlab-ci.yml
MANIFEST.in
Makefile
README.md
requirements.txt
setup.py
test/test_appliance.py
test/test_bulb.py
test/test_main.py
test/test_occupancy.py
tsorb/Appliance.py
tsorb/Bulb.py
tsorb/ElectricalLoadProfile.py
tsorb/Load.py
tsorb/LoadModel.py
tsorb/OccupancyModel.py
tsorb/__init__.py
tsorb.egg-info/PKG-INFO
tsorb.egg-info/SOURCES.txt
tsorb.egg-info/dependency_links.txt
tsorb.egg-info/requires.txt
tsorb.egg-info/top_level.txt
tsorb/data/__init__.py
tsorb/data/activities.csv
tsorb/data/app_act_wd_1.csv
tsorb/data/app_act_wd_2.csv
tsorb/data/app_act_wd_3.csv
tsorb/data/app_act_wd_4.csv
tsorb/data/app_act_wd_5.csv
tsorb/data/app_act_we_1.csv
tsorb/data/app_act_we_2.csv
tsorb/data/app_act_we_3.csv
tsorb/data/app_act_we_4.csv
tsorb/data/app_act_we_5.csv
tsorb/data/appliances.csv
tsorb/data/bulb_number.csv
tsorb/data/bulb_type.csv
tsorb/data/bulbs.csv
tsorb/data/bulbs_duration_config.csv
tsorb/data/bulbs_power.csv
tsorb/data/four_state_24_hour_occupancy.csv
tsorb/data/four_state_starting_state_weekday.csv
tsorb/data/four_state_starting_state_weekend.csv
tsorb/data/four_state_wd_1.csv
tsorb/data/four_state_wd_2.csv
tsorb/data/four_state_wd_3.csv
tsorb/data/four_state_wd_4.csv
tsorb/data/four_state_wd_5.csv
tsorb/data/four_state_wd_6.csv
tsorb/data/four_state_we_1.csv
tsorb/data/four_state_we_2.csv
tsorb/data/four_state_we_3.csv
tsorb/data/four_state_we_4.csv
tsorb/data/four_state_we_5.csv
tsorb/data/four_state_we_6.csv
tsorb/data/irr_try.csv
tsorb/data/irradiance.csv
tsorb/data/occ_act_wd_1.csv
tsorb/data/occ_act_wd_2.csv
tsorb/data/occ_act_wd_3.csv
tsorb/data/occ_act_wd_4.csv
tsorb/data/occ_act_wd_5.csv
tsorb/data/occ_act_we_1.csv
tsorb/data/occ_act_we_2.csv
tsorb/data/occ_act_we_3.csv
tsorb/data/occ_act_we_4.csv
tsorb/data/occ_act_we_5.csv
tsorb/data/occ_sharing_factor.csv
tsorb/data/occ_start_states_weekday.csv
tsorb/data/occ_start_states_weekend.csv
tsorb/data/rel_temperature_modifier.csv
tsorb/utils/ApplianceProbabilityModifier.py
tsorb/utils/Calculations.py
tsorb/utils/DPD.py
tsorb/utils/InputData.py
tsorb/utils/__init__.py