Metadata-Version: 2.1
Name: tsorb
Version: 0.0.2
Summary: Time Series of Occupants in Residential Buildings
Home-page: https://github.com/FZJ-IEK3-VSA/tsorb
Author: Forschungszentrum Juelich GmbH
Author-email: l.kotzur@fz-juelich.de
License: UNKNOWN
Keywords: residential buildings,electricity load,occupancy behavior,markov chain
Platform: UNKNOWN
Classifier: Development Status :: 4 - Beta
Classifier: Intended Audience :: End Users/Desktop
Classifier: Intended Audience :: Science/Research
Classifier: License :: OSI Approved :: GNU General Public License (GPL)
Classifier: Natural Language :: English
Classifier: Operating System :: OS Independent
Classifier: Programming Language :: Python
Classifier: Programming Language :: Python :: 2
Classifier: Programming Language :: Python :: 2.7
Classifier: Programming Language :: Python :: 3
Classifier: Programming Language :: Python :: 3.4
Classifier: Programming Language :: Python :: 3.5
Classifier: Programming Language :: Python :: 3.6
Classifier: Programming Language :: Python :: 3.7
Classifier: Topic :: Scientific/Engineering
Classifier: Topic :: Software Development :: Libraries :: Python Modules
